amifast/__init__.py
amifast/_version.py
amifast/bench.py
amifast/dtypes.py
amifast/format.py
amifast/main.py
amifast/system.py
amifast/utils.py
amifast-0.0.1.dist-info/LICENSE
amifast-0.0.1.dist-info/METADATA
amifast-0.0.1.dist-info/WHEEL
amifast-0.0.1.dist-info/entry_points.txt
amifast-0.0.1.dist-info/top_level.txt
amifast-0.0.1.dist-info/RECORD
